README.md
setup.py
topo_library.egg-info/PKG-INFO
topo_library.egg-info/SOURCES.txt
topo_library.egg-info/dependency_links.txt
topo_library.egg-info/requires.txt
topo_library.egg-info/top_level.txt
topolibrary/__init__.py
topolibrary/model.py
topolibrary/settings.py