Metadata-Version: 1.2
Name: topo-library
Version: 1.45.0
Summary: Topo Utilities Library
Home-page: UNKNOWN
Author: Stelligent
Author-email: contact@stelligent.com
License: UNKNOWN
Platform: UNKNOWN
Requires-Python: >=3.8
